pyqt_instant_search_bar/__init__.py
pyqt_instant_search_bar/instantSearchBar.py
pyqt_instant_search_bar/ico/__init__.py
pyqt_instant_search_bar/ico/search.svg
pyqt_instant_search_bar/style/__init__.py
pyqt_instant_search_bar/style/lineedit.css
pyqt_instant_search_bar/style/search_bar.css
pyqt_instant_search_bar/style/widget.css
pyqt_instant_search_bar-0.0.18.dist-info/LICENSE
pyqt_instant_search_bar-0.0.18.dist-info/METADATA
pyqt_instant_search_bar-0.0.18.dist-info/WHEEL
pyqt_instant_search_bar-0.0.18.dist-info/top_level.txt
pyqt_instant_search_bar-0.0.18.dist-info/RECORD
