Metadata-Version: 2.1
Name: pyqt-instant-search-bar
Version: 0.0.18
Summary: PyQt instant search bar
Home-page: https://github.com/yjg30737/pyqt-instant-search-bar.git
Author: Jung Gyu Yoon
Author-email: yjg30737@gmail.com
License: MIT
License-File: LICENSE
Requires-Dist: PyQt5 (>=5.8)
Requires-Dist: pyqt-resource-helper (>=0.0.1)
Requires-Dist: pyqt-svg-label (>=0.0.1)
